aliyunoss2_autoupload/__init__.py
aliyunoss2_autoupload/__main__.py
aliyunoss2_autoupload/conf.py
aliyunoss2_autoupload/glb.py
aliyunoss2_autoupload/performer.py
aliyunoss2_autoupload/version.py
aliyunoss2_autoupload/data/config-samples/log.yaml
aliyunoss2_autoupload/data/config-samples/log.yml
aliyunoss2_autoupload/data/config-samples/prog.yaml
aliyunoss2_autoupload/data/config-samples/prog.yml
aliyunoss2_autoupload/utils/__init__.py
aliyunoss2_autoupload/utils/loggermixin.py
aliyunoss2_autoupload/utils/strhelper.py
aliyunoss2_autoupload-0.1.dist-info/METADATA
aliyunoss2_autoupload-0.1.dist-info/RECORD
aliyunoss2_autoupload-0.1.dist-info/WHEEL
aliyunoss2_autoupload-0.1.dist-info/entry_points.txt
aliyunoss2_autoupload-0.1.dist-info/namespace_packages.txt
aliyunoss2_autoupload-0.1.dist-info/top_level.txt
