Metadata-Version: 2.1
Name: aliyunoss2-autoupload
Version: 0.1
Summary: Monitor files by wildcard patterns, upload them to ALIYUN OSS, then move to backup directory.
Home-page: https://github.com/tanbro/aliyunoss2-autoupload
Author: liu xue yan
Author-email: liu_xue_yan@foxmail.com
License: AGPLv3+
Keywords: aliyun oss autoupload
Platform: UNKNOWN
Classifier: Development Status :: 5 - Production/Stable
Classifier: Intended Audience :: Developers
Classifier: Intended Audience :: System Administrators
Classifier: Topic :: Internet
Classifier: Topic :: Communications :: File Sharing
Classifier: License :: OSI Approved :: GNU Affero General Public License v3 or later (AGPLv3+)
Classifier: Programming Language :: Python
Classifier: Programming Language :: Python :: 2
Classifier: Programming Language :: Python :: 2.7
Classifier: Programming Language :: Python :: 3
Classifier: Programming Language :: Python :: 3.4
Classifier: Programming Language :: Python :: 3.5
Classifier: Programming Language :: Python :: 3.6
Classifier: Programming Language :: Python :: 3.7
Requires-Python: >=2.7,!=3.0.*,!=3.1.*,!=3.2.*,!=3.3.*
Requires-Dist: oss2 (>=2.2.0)
Requires-Dist: PyYAML (>=3.12)
Requires-Dist: marshmallow (>=3.0.0b1)
Requires-Dist: futures; python_version <= "2.7"
